<?xml version="1.0" encoding="utf-8" ?>
<dwsync>
<file name="fb.png" server="ftp.randomcs.com" local="131063063610000000" remote="131099793600000000" Dst="2" />
<file name="fr.png" server="ftp.randomcs.com" local="131063063610000000" remote="131099793600000000" Dst="2" />
<file name="ig.png" server="ftp.randomcs.com" local="131063063610000000" remote="131099793600000000" Dst="2" />
<file name="post.png" server="ftp.randomcs.com" local="131063063620000000" remote="131099793600000000" Dst="2" />
<file name="revolution_slide1.png" server="ftp.randomcs.com" local="131063063620000000" remote="131099793600000000" Dst="2" />
<file name="revolution_slide2.png" server="ftp.randomcs.com" local="131063063610000000" remote="131099793600000000" Dst="2" />
<file name="tw.png" server="ftp.randomcs.com" local="131063063610000000" remote="131099793600000000" Dst="2" />
<file name="vm.png" server="ftp.randomcs.com" local="131063063610000000" remote="131099794200000000" Dst="2" />
<file name="yt.png" server="ftp.randomcs.com" local="131063063610000000" remote="131099794200000000" Dst="2" />
<file name="wc.png" server="ftp.randomcs.com" local="131063063610000000" remote="131099794200000000" Dst="2" />
</dwsync>